[
  {
    "reason": "Invalid outside polygon (missing amenity=charging_station)",
    "point_id": "node/11896601090",
    "polygon_id": "N/A",
    "properties": {
      "access": "yes",
      "authentication:app": "yes",
      "authentication:membership_card": "yes",
      "authentication:none": "no",
      "brand": "Hexagonal Ocean",
      "capacity": "2",
      "email": "geral@hexagonalocean.pt",
      "fee": "yes",
      "man_made": "charge_point",
      "maxstay": "unlimited",
      "motorcar": "yes",
      "network": "Mobi.E",
      "opening_hours": "24/7",
      "operator": "Hexagonal Ocean",
      "parking:fee": "no",
      "payment:app": "yes",
      "payment:cards": "no",
      "payment:cash": "no",
      "payment:membership_card": "yes",
      "ref": "LSB-00829",
      "ref:EU:EVSE": "PT*HEX*E*LSB*00829*01;PT*HEX*E*LSB*00829*02",
      "socket:type2": "2",
      "socket:type2:current": "16",
      "socket:type2:output": "11 kW",
      "socket:type2:voltage": "400",
      "website": "https://www.mobie.pt/",
      "id": "node/11896601090"
    }
  },
  {
    "reason": "Invalid outside polygon (missing amenity=charging_station)",
    "point_id": "node/12489874527",
    "polygon_id": "N/A",
    "properties": {
      "access": "yes",
      "authentication:app": "yes",
      "authentication:membership_card": "yes",
      "authentication:none": "no",
      "brand": "Hexagonal Ocean",
      "capacity": "2",
      "email": "geral@hexagonalocean.pt",
      "fee": "yes",
      "man_made": "charge_point",
      "maxstay": "unlimited",
      "motorcar": "yes",
      "network": "Mobi.E",
      "opening_hours": "24/7",
      "operator": "Hexagonal Ocean",
      "parking:fee": "no",
      "payment:app": "yes",
      "payment:cards": "no",
      "payment:cash": "no",
      "payment:membership_card": "yes",
      "ref": "LSB-00830",
      "ref:EU:EVSE": "PT*HEX*E*LSB*00830*01;PT*HEX*E*LSB*00830*02",
      "socket:type2": "2",
      "socket:type2:current": "16",
      "socket:type2:output": "11 kW",
      "socket:type2:voltage": "400",
      "website": "https://www.mobie.pt/",
      "id": "node/12489874527"
    }
  }
]